SPARQLWrapper/KeyCaseInsensitiveDict.py
SPARQLWrapper/SPARQLExceptions.py
SPARQLWrapper/SmartWrapper.py
SPARQLWrapper/Wrapper.py
SPARQLWrapper/__init__.py
SPARQLWrapper.skipssl-1.8.9.dist-info/AUTHORS.md
SPARQLWrapper.skipssl-1.8.9.dist-info/LICENSE.txt
SPARQLWrapper.skipssl-1.8.9.dist-info/METADATA
SPARQLWrapper.skipssl-1.8.9.dist-info/WHEEL
SPARQLWrapper.skipssl-1.8.9.dist-info/top_level.txt
SPARQLWrapper.skipssl-1.8.9.dist-info/RECORD
